{
   "_embedded":{
      "items":[
         {
            "_links":{
               "self":{
                  "href":"http://hmg.snc.cultura.gov.br/api/v2/sistemadeculturalocal/3974/?format=json"
               }
            },
            "_embedded":{
               "ente_federado":{
                  "cod_ibge":1500107,
                  "nome":"Abaetetuba",
                  "territorio":"1610.404",
                  "populacao":156292,
                  "idh":"0.628",
                  "is_municipio":true,
                  "sigla":"PA"
               },
               "governo":{
                  "email_institucional":"pactopelavontadepopular@hotmail.com",
                  "nome_prefeito":"ALCIDES EUFRASIO DA CONCEIÇÃO NEGRÃO",
                  "termo_posse_prefeito":""
               },
               "conselho":null,
               "sede":{
                  "localizacao":{
                     "cnpj":"05105127000199",
                     "endereco":"RUA SIQUEIRA MENDES 1.359",
                     "cep":"68440-000",
                     "bairro":" CENTRO",
                     "complemento":""
                  },
                  "telefones":{
                     "telefone_um":"37512022",
                     "telefone_dois":"",
                     "telefone_tres":""
                  },
                  "endereco_eletronico":null
               }
            },
            "id":3974,
            "data_adesao":"2013-06-03",
            "situacao_adesao":"Publicado no DOU",
            "cod_situacao_adesao":"6",
            "acoes_plano_trabalho":{
               "_links":{
                  "self":{
                     "href":"http://hmg.snc.cultura.gov.br/api/v2/acoesplanotrabalho/3974/?format=json"
                  }
               },
               "_embedded":{
                  "criacao_lei_sistema": {
                     "cod_situacao": "4",
                     "situacao": "Arquivo danificado",
                     "data_envio": "2018-08-17",
                     "arquivo": "http://hmg.snc.cultura.gov.br/media/3846/docs/orgaogestor/lei_-_197__2013_-_dispoe_sobre_a_reestruturacao_administrativa_mun_mj3hutC.pdf"
                  },
                  "criacao_orgao_gestor":null,
                  "criacao_plano_cultura":null,
                  "criacao_fundo_cultura":null,
                  "criacao_conselho_cultural":null
               },
               "id":3974
            }
         },
      ]
   },
   "count":2755,
   "page_size":1,
   "municipios":2730,
   "municipios_aderidos":2730,
   "estados":25,
   "estados_aderidos":25
}